copy_to/__init__.py
copy_to-1.4.9.dist-info/LICENSE
copy_to-1.4.9.dist-info/METADATA
copy_to-1.4.9.dist-info/WHEEL
copy_to-1.4.9.dist-info/entry_points.txt
copy_to-1.4.9.dist-info/top_level.txt
copy_to-1.4.9.dist-info/RECORD
