Metadata-Version: 2.2
Name: copy-to
Version: 1.4.9
Summary: A little commandline tool to copy and paste multiple files and directories to single directory with use of configuration
Author-email: Excited Bore <brunt-curry-wobble@duck.com>
Project-URL: Homepage, https://github.com/excited-bore/copy-to
Project-URL: Bug Tracker, https://github.com/excited-bore/copy-to/issues
Keywords: copy-to,setuptools,development
Classifier: Programming Language :: Python :: 3
Classifier: License :: OSI Approved :: MIT License
Classifier: Operating System :: OS Independent
Requires-Python: >=3.7
License-File: LICENSE
Requires-Dist: argcomplete>=3.2.1
Requires-Dist: GitPython>=3.1.14
Requires-Dist: prompt_toolkit>=3.0.20
